envmanager/__init__.py
envmanager/cli.py
envmanager/core.py
envmanager_package-0.1.0.dist-info/METADATA
envmanager_package-0.1.0.dist-info/WHEEL
envmanager_package-0.1.0.dist-info/entry_points.txt
envmanager_package-0.1.0.dist-info/top_level.txt
envmanager_package-0.1.0.dist-info/RECORD
